{"meta": {"p1": 0.11, "p2": 0.55}, "size": 28, "males_pref": {"M0": {"W12": 0, "W9": 1, "W21": 1, "W15": 1, "W24": 4}, "M1": {"W23": 0, "W18": 1, "W6": 1, "W10": 3, "W25": 4}, "M2": {"W16": 0, "W8": 1, "W13": 2, "W19": 3, "W15": 4}, "M3": {"W18": 0, "W11": 1, "W27": 2, "W9": 3, "W4": 3}, "M4": {"W21": 0, "W11": 1, "W4": 2, "W0": 2, "W2": 4}, "M5": {"W13": 0, "W5": 1, "W24": 2}, "M6": {"W15": 0, "W9": 0, "W2": 2, "W7": 2, "W19": 2, "W8": 5}, "M7": {"W5": 0, "W25": 0, "W7": 2, "W9": 3}, "M8": {"W15": 0, "W14": 1, "W13": 2, "W22": 3, "W5": 3}, "M9": {"W26": 0, "W8": 0, "W12": 0, "W21": 3, "W6": 4}, "M10": {"W21": 0, "W6": 0, "W7": 0, "W10": 0, "W14": 4}, "M11": {"W8": 0, "W2": 0, "W23": 0, "W10": 0, "W9": 4, "W5": 5}, "M12": {"W12": 0, "W19": 0, "W8": 2, "W13": 3, "W22": 3, "W3": 3, "W27": 3}, "M13": {"W0": 0, "W23": 0, "W4": 2, "W20": 3}, "M14": {"W5": 0, "W25": 1, "W17": 2, "W19": 2, "W3": 4, "W0": 4, "W11": 4, "W12": 4}, "M15": {"W25": 0, "W13": 1, "W14": 1}, "M16": {"W24": 0, "W26": 1, "W14": 2, "W13": 2}, "M17": {"W27": 0, "W15": 1, "W11": 2, "W9": 2, "W1": 4, "W19": 4, "W24": 6}, "M18": {"W27": 0, "W22": 1, "W6": 2, "W10": 2, "W15": 4, "W25": 4}, "M19": {"W12": 0, "W20": 1, "W7": 1, "W26": 1, "W22": 1, "W3": 5, "W25": 5, "W5": 5}, "M20": {"W12": 0, "W26": 1, "W6": 2, "W1": 3, "W4": 3, "W16": 5}, "M21": {"W20": 0, "W5": 0, "W7": 0, "W25": 0, "W19": 4}, "M22": {"W23": 0, "W21": 0, "W5": 0, "W17": 3, "W6": 3}, "M23": {"W12": 0, "W20": 1, "W8": 1, "W3": 1, "W6": 1, "W2": 1}, "M24": {"W6": 0, "W20": 1, "W26": 2}, "M25": {"W20": 0, "W5": 1, "W21": 1, "W26": 3, "W10": 4, "W9": 4}, "M26": {"W24": 0, "W26": 1, "W0": 1, "W8": 1}, "M27": {"W8": 0, "W4": 0, "W1": 0}}, "females_pref": {"W0": {"M17": 0, "M20": 0, "M2": 0, "M21": 0, "M16": 4}, "W1": {"M6": 0, "M0": 1, "M12": 2}, "W2": {"M8": 0, "M26": 1, "M17": 2, "M7": 2, "M16": 4}, "W3": {"M23": 0, "M11": 0, "M26": 0, "M17": 3, "M3": 3, "M16": 3, "M8": 3, "M22": 7}, "W4": {"M0": 0, "M17": 0, "M7": 2, "M19": 3, "M21": 3}, "W5": {"M14": 0, "M4": 1, "M17": 1, "M9": 3, "M7": 3}, "W6": {"M0": 0, "M21": 1, "M24": 1, "M3": 1, "M5": 1}, "W7": {"M27": 0, "M14": 1, "M11": 2, "M13": 3, "M16": 4, "M21": 5}, "W8": {"M5": 0, "M23": 1, "M4": 1, "M2": 3}, "W9": {"M3": 0, "M22": 1, "M4": 1, "M27": 3, "M6": 4, "M0": 5}, "W10": {"M11": 0, "M12": 1, "M17": 2, "M9": 2}, "W11": {"M3": 0, "M4": 1, "M15": 2, "M25": 3}, "W12": {"M20": 0, "M7": 0, "M22": 0, "M3": 3, "M19": 4}, "W13": {"M16": 0, "M1": 1, "M10": 2}, "W14": {"M25": 0, "M15": 1, "M17": 1, "M18": 3}, "W15": {"M12": 0, "M8": 0, "M3": 0, "M10": 3, "M5": 4}, "W16": {"M7": 0, "M0": 1, "M10": 1, "M18": 1, "M27": 4}, "W17": {"M0": 0, "M20": 0, "M8": 2, "M4": 3, "M11": 3}, "W18": {"M6": 0, "M16": 0, "M22": 2, "M18": 3, "M14": 4, "M1": 4, "M24": 6}, "W19": {"M21": 0, "M9": 1, "M4": 2, "M1": 3, "M8": 3}, "W20": {"M23": 0, "M14": 1, "M21": 2, "M25": 2, "M1": 4, "M20": 5}, "W21": {"M3": 0, "M16": 0, "M6": 2, "M4": 3, "M17": 3}, "W22": {"M18": 0, "M1": 0, "M26": 0, "M0": 0, "M27": 0}, "W23": {"M24": 0, "M8": 1, "M10": 2, "M20": 2}, "W24": {"M21": 0, "M7": 1, "M3": 1, "M27": 1}, "W25": {"M15": 0, "M27": 1, "M4": 2}, "W26": {"M6": 0, "M4": 0, "M26": 0, "M3": 0, "M14": 0, "M9": 0, "M12": 0}, "W27": {"M1": 0, "M7": 1, "M15": 1, "M25": 3}}, "possible_solutions": []}