{"meta": {"p1": 0.17, "p2": 0.71}, "size": 28, "males_pref": {"M0": {"W4": 0, "W2": 0}, "M1": {"W12": 0, "W5": 1, "W27": 2, "W18": 3, "W24": 4, "W22": 5, "W7": 6, "W19": 7}, "M2": {"W11": 0, "W3": 1, "W20": 1, "W24": 3}, "M3": {"W21": 0, "W18": 1, "W22": 2, "W14": 3, "W6": 3, "W7": 5, "W1": 6, "W3": 7}, "M4": {"W25": 0, "W2": 1, "W21": 2, "W6": 2}, "M5": {"W18": 0, "W2": 0, "W21": 2}, "M6": {"W16": 0, "W17": 1, "W22": 2, "W14": 3, "W9": 4, "W1": 4}, "M7": {"W3": 0, "W8": 0, "W18": 2, "W24": 2, "W21": 4, "W14": 5, "W7": 6, "W27": 6, "W15": 8, "W2": 9}, "M8": {"W0": 0, "W21": 1, "W19": 1, "W22": 3, "W5": 3, "W9": 5}, "M9": {"W27": 0, "W13": 1, "W22": 2, "W0": 3, "W15": 3, "W19": 3, "W6": 6, "W21": 6, "W25": 8}, "M10": {"W25": 0, "W17": 1, "W10": 1, "W22": 3, "W0": 3, "W27": 5, "W7": 6, "W12": 7}, "M11": {"W4": 0, "W0": 1, "W10": 1, "W17": 3, "W5": 4, "W3": 4, "W23": 6}, "M12": {"W23": 0, "W9": 1, "W16": 1, "W14": 3, "W26": 4, "W6": 5}, "M13": {"W2": 0, "W3": 0, "W17": 2, "W25": 2, "W16": 4, "W18": 5, "W15": 5, "W13": 5, "W5": 5, "W24": 9}, "M14": {"W13": 0, "W17": 1, "W4": 1, "W0": 3, "W22": 4, "W25": 5, "W12": 6, "W27": 7, "W21": 8}, "M15": {"W4": 0, "W3": 1, "W5": 1, "W26": 1, "W12": 4, "W14": 5}, "M16": {"W17": 0, "W23": 1, "W2": 1, "W18": 1, "W27": 1, "W13": 1, "W6": 6}, "M17": {"W23": 0, "W16": 1, "W1": 2, "W8": 2, "W17": 4, "W26": 4, "W6": 6}, "M18": {"W9": 0, "W26": 0, "W6": 2, "W12": 3, "W19": 4, "W14": 5, "W21": 6, "W4": 6, "W13": 6, "W16": 9}, "M19": {"W17": 0, "W7": 0, "W15": 2, "W26": 2, "W23": 4}, "M20": {"W4": 0, "W2": 0, "W23": 2, "W19": 2, "W22": 2, "W26": 5, "W17": 6}, "M21": {"W4": 0, "W8": 1, "W18": 2, "W20": 2, "W6": 2, "W16": 5, "W19": 6, "W3": 7, "W21": 8}, "M22": {"W9": 0, "W13": 1, "W6": 1, "W24": 3, "W23": 4, "W27": 5, "W11": 6}, "M23": {"W27": 0, "W2": 0, "W9": 2, "W18": 2, "W10": 4, "W13": 5, "W25": 6, "W24": 6, "W3": 6, "W23": 9}, "M24": {"W17": 0, "W25": 0, "W14": 2, "W22": 2, "W10": 4, "W13": 4, "W18": 6, "W20": 7}, "M25": {"W16": 0, "W18": 0, "W19": 0, "W13": 3, "W22": 4, "W2": 5, "W0": 6}, "M26": {"W12": 0, "W27": 1, "W15": 1, "W19": 3, "W14": 4}, "M27": {"W8": 0, "W4": 1, "W20": 2, "W1": 3, "W18": 3, "W5": 5, "W13": 5, "W15": 7, "W24": 7}}, "females_pref": {"W0": {"M4": 0, "M22": 0, "M0": 2, "M16": 2, "M5": 4, "M12": 4}, "W1": {"M8": 0, "M14": 0, "M20": 0, "M23": 0}, "W2": {"M16": 0, "M21": 1, "M27": 2, "M13": 2}, "W3": {"M19": 0, "M27": 1, "M24": 1, "M25": 3, "M1": 3}, "W4": {"M5": 0, "M25": 1, "M21": 2, "M0": 3, "M14": 4, "M16": 5, "M19": 6, "M24": 6, "M23": 8}, "W5": {"M26": 0, "M23": 0, "M1": 2, "M17": 3}, "W6": {"M9": 0, "M19": 1, "M7": 2, "M8": 3, "M26": 4, "M6": 5, "M23": 6}, "W7": {"M24": 0, "M3": 0, "M23": 2, "M19": 2, "M27": 4, "M17": 5, "M1": 6, "M4": 7, "M10": 7}, "W8": {"M4": 0, "M18": 1, "M22": 1, "M10": 1, "M6": 4}, "W9": {"M10": 0, "M16": 1, "M2": 2, "M24": 2, "M26": 4, "M13": 5}, "W10": {"M9": 0, "M18": 1, "M10": 2, "M24": 3, "M5": 3}, "W11": {"M15": 0, "M22": 1, "M6": 2, "M20": 3, "M3": 3, "M23": 3, "M11": 6, "M0": 7, "M12": 8}, "W12": {"M14": 0, "M18": 1, "M10": 1, "M24": 1, "M5": 1, "M20": 5, "M7": 6, "M4": 7, "M27": 7}, "W13": {"M8": 0, "M18": 1, "M12": 2, "M17": 3, "M7": 4, "M2": 5}, "W14": {"M25": 0, "M6": 1, "M1": 1, "M20": 3, "M22": 4, "M0": 4}, "W15": {"M3": 0, "M17": 1, "M4": 1, "M8": 1}, "W16": {"M26": 0, "M9": 1, "M17": 2, "M25": 3}, "W17": {"M2": 0, "M27": 0, "M19": 0, "M4": 3, "M18": 4}, "W18": {"M13": 0, "M23": 1, "M15": 1, "M3": 3, "M27": 4, "M8": 5, "M0": 6}, "W19": {"M25": 0, "M4": 1, "M1": 2, "M16": 3}, "W20": {"M4": 0, "M26": 1, "M13": 2, "M20": 3, "M18": 3, "M15": 3, "M22": 6, "M24": 7}, "W21": {"M6": 0, "M19": 1, "M16": 1, "M14": 3, "M11": 4, "M13": 5, "M1": 5, "M7": 7, "M27": 8, "M25": 9}, "W22": {"M23": 0, "M5": 1, "M20": 2, "M17": 3}, "W23": {"M15": 0, "M6": 0, "M7": 2, "M9": 3, "M26": 4, "M17": 4, "M23": 6, "M13": 7, "M27": 8}, "W24": {"M20": 0, "M27": 1, "M19": 2, "M15": 2}, "W25": {"M0": 0, "M10": 1, "M19": 1, "M24": 3, "M16": 4, "M9": 4, "M14": 4, "M20": 4}, "W26": {"M1": 0, "M17": 0, "M3": 2, "M4": 3, "M8": 4, "M26": 4, "M0": 6, "M22": 7, "M13": 8, "M19": 9}, "W27": {"M10": 0, "M1": 1, "M23": 1, "M18": 1, "M12": 4, "M3": 5, "M17": 6, "M26": 7, "M20": 8}}, "possible_solutions": []}