{"meta": {"p1": 0.72, "p2": 0.12}, "size": 26, "males_pref": {"M0": {"W22": 0, "W0": 0, "W17": 0, "W19": 0, "W14": 0, "W4": 0, "W1": 0, "W23": 0, "W24": 0, "W13": 0, "W7": 0, "W16": 11, "W15": 11, "W20": 11, "W3": 11, "W6": 15, "W5": 15, "W18": 15, "W25": 15}, "M1": {"W5": 0, "W2": 0, "W0": 0, "W17": 0, "W14": 0, "W9": 0, "W16": 0, "W11": 0, "W12": 0, "W1": 0, "W13": 0, "W4": 0}, "M2": {"W0": 0, "W5": 0, "W20": 0, "W12": 0, "W9": 0, "W21": 0, "W17": 0, "W16": 0, "W2": 0, "W10": 0, "W3": 0, "W8": 0, "W11": 12, "W7": 12, "W23": 12, "W15": 12, "W1": 12, "W19": 12, "W4": 12, "W22": 12}, "M3": {"W24": 0, "W18": 0, "W9": 0, "W7": 0, "W3": 0, "W11": 0, "W20": 0, "W15": 0, "W21": 0, "W10": 0, "W4": 0, "W5": 0, "W17": 12, "W6": 13, "W12": 13, "W19": 13}, "M4": {"W14": 0, "W24": 0, "W0": 0, "W10": 0, "W25": 0, "W2": 0, "W7": 0, "W6": 0, "W8": 0, "W3": 0, "W13": 0, "W9": 0, "W23": 0, "W20": 0, "W17": 0, "W4": 0, "W19": 0, "W5": 0, "W21": 0, "W18": 0, "W11": 0}, "M5": {"W14": 0, "W7": 0, "W17": 0, "W12": 3, "W16": 3, "W18": 3, "W2": 3, "W1": 3, "W6": 3, "W3": 3, "W9": 3, "W23": 3, "W5": 3, "W4": 3, "W15": 3, "W13": 3, "W20": 16}, "M6": {"W17": 0, "W25": 0, "W1": 0, "W20": 3, "W24": 3, "W10": 5, "W5": 6, "W16": 6, "W15": 6, "W12": 6, "W14": 6, "W4": 11, "W8": 11, "W6": 11, "W3": 11, "W2": 11, "W7": 16, "W11": 16, "W0": 16}, "M7": {"W18": 0, "W12": 0, "W0": 0, "W9": 0, "W3": 0, "W2": 5, "W24": 5, "W15": 5, "W19": 5, "W25": 5, "W16": 5, "W4": 5, "W5": 5, "W1": 5, "W7": 5, "W13": 5, "W8": 5, "W21": 5, "W11": 5, "W14": 19}, "M8": {"W13": 0, "W15": 0, "W8": 0, "W11": 0, "W10": 0, "W17": 0, "W5": 0, "W19": 0, "W3": 0, "W16": 9, "W6": 9, "W9": 11, "W25": 11, "W22": 11, "W14": 11, "W4": 11, "W21": 16}, "M9": {"W24": 0, "W6": 0, "W16": 0, "W20": 0, "W3": 0, "W2": 0, "W14": 0, "W8": 0, "W11": 0, "W0": 0, "W19": 0, "W9": 0, "W21": 0, "W15": 0, "W18": 0, "W23": 0, "W7": 0, "W1": 0, "W17": 0}, "M10": {"W5": 0, "W10": 1, "W12": 1, "W3": 1, "W2": 1, "W13": 1, "W11": 1, "W0": 1, "W19": 1, "W15": 1, "W1": 1, "W16": 1, "W9": 1, "W4": 13, "W20": 13, "W25": 13, "W14": 13, "W24": 13, "W17": 13, "W18": 19, "W8": 19, "W6": 19, "W21": 19, "W22": 19, "W7": 24}, "M11": {"W16": 0, "W14": 0, "W2": 0, "W7": 0, "W21": 0, "W17": 0, "W13": 0, "W6": 0, "W19": 0, "W20": 0, "W18": 0, "W10": 0, "W4": 0, "W12": 0, "W9": 0, "W0": 0}, "M12": {"W25": 0, "W16": 0, "W8": 0, "W4": 0, "W9": 0, "W15": 0, "W18": 0, "W6": 0, "W20": 0, "W0": 0, "W12": 0, "W7": 0, "W17": 12, "W13": 12, "W3": 12, "W1": 12, "W22": 12, "W23": 12, "W2": 12, "W24": 12, "W21": 12, "W14": 12}, "M13": {"W24": 0, "W21": 0, "W17": 0, "W23": 0, "W7": 0, "W4": 0, "W19": 0, "W0": 0, "W18": 0, "W2": 0, "W14": 0, "W10": 0, "W25": 0, "W12": 0, "W6": 0, "W11": 0}, "M14": {"W4": 0, "W2": 0, "W22": 0, "W11": 0, "W13": 0, "W8": 0, "W25": 0, "W1": 0, "W14": 0, "W0": 9, "W20": 9, "W12": 9, "W9": 9, "W18": 9, "W21": 9, "W23": 9}, "M15": {"W3": 0, "W6": 0, "W17": 0, "W9": 0, "W10": 0, "W1": 0, "W25": 0, "W12": 0, "W5": 0, "W2": 0, "W13": 10, "W19": 10, "W4": 10, "W22": 10, "W14": 10, "W18": 10, "W16": 10, "W8": 10, "W24": 10, "W7": 10}, "M16": {"W10": 0, "W20": 1, "W6": 2, "W17": 3, "W9": 4, "W24": 4, "W2": 4, "W12": 4, "W4": 4, "W14": 4, "W11": 4, "W5": 4, "W7": 4, "W19": 4, "W25": 4, "W22": 4, "W1": 4}, "M17": {"W18": 0, "W6": 0, "W11": 0, "W10": 3, "W15": 4, "W19": 5, "W16": 5, "W17": 7, "W8": 8, "W22": 8, "W4": 10, "W5": 10, "W23": 10, "W13": 10, "W20": 10, "W0": 10}, "M18": {"W23": 0, "W4": 0, "W8": 0, "W13": 0, "W14": 0, "W11": 0, "W3": 0, "W25": 7, "W24": 7, "W15": 7, "W1": 7, "W0": 11, "W20": 11, "W19": 11, "W10": 11, "W21": 11, "W9": 11, "W2": 11}, "M19": {"W22": 0, "W12": 0, "W20": 0, "W7": 0, "W2": 0, "W11": 0, "W9": 0, "W16": 0, "W23": 0, "W24": 0, "W15": 0, "W10": 11, "W6": 11, "W14": 11, "W0": 11, "W21": 11, "W4": 11, "W5": 11, "W19": 11, "W18": 11}, "M20": {"W14": 0, "W8": 0, "W12": 2, "W4": 2, "W24": 4, "W25": 4, "W9": 4, "W18": 4, "W19": 4, "W20": 4, "W1": 4, "W21": 4, "W5": 12, "W7": 12, "W10": 12, "W13": 12}, "M21": {"W0": 0, "W22": 0, "W3": 0, "W14": 3, "W17": 4, "W25": 4, "W16": 4, "W12": 7, "W23": 7, "W24": 9, "W11": 9, "W13": 11, "W9": 12, "W15": 12, "W6": 12, "W8": 12, "W4": 12, "W18": 12, "W19": 12, "W2": 12}, "M22": {"W14": 0, "W13": 1, "W18": 1, "W17": 1, "W22": 1, "W8": 5, "W4": 5, "W11": 7, "W3": 7, "W0": 7, "W12": 7, "W15": 7, "W24": 7, "W25": 7, "W2": 7, "W16": 7, "W5": 7}, "M23": {"W8": 0, "W0": 0, "W6": 0, "W15": 0, "W25": 0, "W23": 0, "W3": 0, "W2": 0, "W20": 0, "W17": 9, "W12": 9, "W14": 9, "W1": 9, "W10": 13, "W21": 13, "W4": 13, "W9": 13, "W18": 13, "W22": 13, "W16": 13}, "M24": {"W4": 0, "W11": 0, "W5": 2, "W3": 2, "W16": 2, "W14": 2, "W10": 2, "W2": 2, "W24": 2, "W15": 2, "W7": 2, "W1": 2, "W25": 2, "W20": 2, "W6": 2, "W18": 2, "W0": 2, "W19": 2}, "M25": {"W1": 0, "W11": 0, "W9": 0, "W16": 0, "W22": 0, "W6": 5, "W14": 6, "W19": 7, "W12": 7, "W10": 7, "W18": 7, "W8": 11, "W2": 12, "W3": 12, "W25": 12, "W0": 15, "W13": 15, "W17": 15, "W23": 18}}, "females_pref": {"W0": {"M18": 0, "M17": 0, "M2": 0, "M16": 0, "M9": 0, "M6": 5, "M12": 5, "M15": 5, "M11": 8, "M8": 8, "M20": 8, "M19": 8, "M22": 12, "M10": 12, "M5": 12, "M24": 12}, "W1": {"M19": 0, "M24": 0, "M0": 0, "M4": 0, "M7": 0, "M18": 0, "M3": 0, "M25": 0, "M17": 0, "M9": 0, "M20": 0, "M23": 0, "M22": 0, "M12": 13, "M11": 13, "M14": 13, "M6": 13, "M15": 13, "M1": 13, "M21": 13, "M2": 13, "M10": 13, "M16": 13, "M13": 13}, "W2": {"M7": 0, "M24": 1, "M19": 1, "M15": 1, "M11": 1, "M14": 1, "M23": 1, "M2": 1, "M20": 1, "M0": 1, "M9": 1, "M17": 1, "M1": 1, "M13": 1, "M8": 1, "M12": 1, "M4": 1, "M25": 1, "M6": 1, "M16": 1, "M3": 1, "M21": 1}, "W3": {"M5": 0, "M7": 0, "M15": 0, "M8": 3, "M18": 3, "M9": 3, "M11": 3, "M13": 3, "M20": 3, "M22": 9, "M0": 10, "M2": 11, "M23": 11, "M21": 11, "M19": 14}, "W4": {"M21": 0, "M4": 0, "M20": 2, "M23": 3, "M15": 3, "M3": 3, "M1": 6, "M17": 6, "M24": 6, "M7": 6, "M14": 10, "M11": 10, "M25": 12, "M19": 13, "M2": 13, "M18": 13, "M12": 13, "M16": 17, "M10": 17, "M0": 17, "M9": 17, "M22": 17}, "W5": {"M24": 0, "M11": 0, "M22": 0, "M25": 0, "M3": 0, "M18": 0, "M10": 0, "M14": 0, "M21": 0, "M13": 0, "M15": 10, "M7": 10, "M23": 10, "M19": 10, "M5": 10, "M16": 10, "M12": 10, "M0": 10, "M6": 18, "M8": 18, "M9": 18, "M17": 18}, "W6": {"M7": 0, "M10": 0, "M13": 0, "M0": 0, "M21": 0, "M5": 0, "M11": 6, "M8": 6, "M22": 6, "M15": 6, "M16": 6, "M25": 6, "M4": 12, "M17": 12, "M18": 12, "M12": 12, "M19": 12}, "W7": {"M17": 0, "M10": 0, "M20": 0, "M9": 0, "M12": 0, "M19": 0, "M25": 0, "M11": 0, "M24": 0, "M21": 9, "M13": 10, "M6": 10, "M8": 10, "M22": 10, "M4": 10, "M14": 10, "M15": 10, "M5": 10, "M0": 10, "M23": 19, "M2": 20}, "W8": {"M15": 0, "M3": 0, "M21": 0, "M17": 0, "M5": 0, "M0": 0, "M23": 6, "M10": 6, "M11": 8, "M7": 8, "M20": 8, "M24": 8, "M13": 8, "M8": 8, "M16": 8, "M18": 8, "M2": 8, "M6": 8, "M12": 8}, "W9": {"M3": 0, "M22": 1, "M16": 1, "M14": 1, "M5": 1, "M1": 1, "M4": 1, "M2": 7, "M21": 7, "M19": 9, "M8": 9, "M7": 9, "M11": 9, "M13": 13, "M17": 13, "M23": 13, "M9": 16, "M25": 17, "M12": 17, "M20": 17}, "W10": {"M17": 0, "M19": 0, "M22": 0, "M2": 0, "M16": 0, "M7": 0, "M6": 0, "M25": 0, "M8": 0, "M12": 0, "M15": 0, "M3": 0, "M5": 0, "M11": 0, "M13": 0, "M24": 0, "M23": 0, "M20": 0, "M9": 0}, "W11": {"M9": 0, "M4": 0, "M2": 2, "M15": 2, "M16": 2, "M0": 2, "M22": 2, "M1": 2, "M20": 2, "M11": 2, "M8": 10, "M7": 10, "M21": 10, "M24": 10, "M3": 10, "M19": 15, "M14": 15, "M13": 15}, "W12": {"M5": 0, "M11": 0, "M1": 0, "M2": 0, "M4": 0, "M24": 0, "M15": 0, "M18": 7, "M20": 7, "M13": 7, "M22": 7, "M10": 7, "M12": 7, "M21": 13, "M25": 13, "M8": 13, "M17": 13, "M9": 17}, "W13": {"M4": 0, "M9": 1, "M2": 1, "M13": 1, "M8": 1, "M22": 1, "M14": 6, "M17": 6, "M25": 6, "M21": 6, "M12": 6, "M1": 6, "M0": 6, "M19": 6, "M24": 6, "M16": 6, "M20": 6, "M6": 6}, "W14": {"M3": 0, "M14": 0, "M20": 0, "M10": 0, "M11": 0, "M2": 5, "M19": 5, "M16": 5, "M12": 5, "M24": 5, "M7": 5, "M6": 5, "M15": 5, "M13": 5, "M25": 5, "M0": 5, "M17": 5, "M1": 5}, "W15": {"M11": 0, "M12": 0, "M22": 0, "M16": 0, "M13": 0, "M18": 0, "M1": 0, "M7": 0, "M20": 8, "M9": 8, "M8": 8, "M3": 11, "M19": 11, "M21": 11, "M4": 11, "M24": 11, "M5": 11}, "W16": {"M25": 0, "M1": 0, "M6": 0, "M14": 3, "M22": 3, "M5": 3, "M0": 3, "M10": 3, "M3": 3, "M23": 3, "M19": 3, "M7": 3, "M24": 3, "M9": 3, "M20": 14, "M17": 14, "M15": 14, "M16": 14, "M21": 14, "M2": 14, "M4": 20, "M18": 20}, "W17": {"M24": 0, "M5": 0, "M4": 0, "M21": 0, "M2": 0, "M8": 0, "M16": 0, "M14": 0, "M20": 0, "M19": 0, "M6": 0, "M1": 0, "M9": 0, "M18": 0, "M17": 0, "M11": 0, "M25": 0, "M15": 0, "M13": 0, "M7": 19, "M0": 19, "M3": 19}, "W18": {"M10": 0, "M20": 0, "M0": 0, "M3": 0, "M25": 0, "M24": 0, "M5": 0, "M18": 0, "M23": 8, "M8": 8, "M16": 8, "M15": 8, "M19": 8, "M14": 8, "M4": 8, "M7": 8, "M1": 8, "M12": 8, "M6": 8, "M9": 8, "M13": 8}, "W19": {"M10": 0, "M16": 0, "M21": 0, "M1": 0, "M5": 0, "M17": 0, "M6": 0, "M13": 7, "M14": 7, "M18": 7, "M4": 7, "M23": 7, "M12": 7, "M8": 7, "M20": 7, "M19": 7, "M3": 7, "M25": 17, "M0": 17, "M15": 19}, "W20": {"M17": 0, "M6": 1, "M19": 1, "M21": 1, "M22": 1, "M24": 1, "M16": 6, "M10": 6, "M3": 6, "M25": 6, "M2": 6, "M8": 6, "M11": 6, "M12": 6, "M18": 6, "M7": 6, "M9": 6}, "W21": {"M8": 0, "M13": 0, "M12": 0, "M3": 0, "M1": 0, "M5": 0, "M19": 0, "M14": 0, "M18": 0, "M15": 0, "M9": 0, "M6": 0, "M4": 0, "M2": 0, "M11": 0, "M7": 0, "M17": 0, "M22": 0, "M10": 0, "M24": 19, "M16": 19}, "W22": {"M4": 0, "M13": 0, "M23": 0, "M15": 0, "M8": 4, "M19": 4, "M1": 4, "M24": 4, "M9": 4, "M3": 9, "M10": 9, "M16": 9, "M20": 9, "M5": 9, "M11": 9, "M25": 9, "M17": 9, "M21": 9, "M2": 9}, "W23": {"M12": 0, "M5": 0, "M15": 2, "M16": 2, "M14": 2, "M21": 5, "M7": 5, "M18": 5, "M17": 5, "M20": 5, "M19": 5, "M4": 5, "M24": 5, "M22": 5, "M23": 5, "M1": 5, "M0": 5, "M9": 5, "M8": 5}, "W24": {"M2": 0, "M17": 0, "M21": 0, "M9": 0, "M8": 0, "M20": 0, "M22": 0, "M3": 0, "M15": 0, "M13": 0, "M18": 0, "M7": 0, "M25": 0, "M4": 0, "M10": 0, "M1": 0, "M6": 0, "M12": 0, "M11": 0}, "W25": {"M7": 0, "M1": 0, "M19": 0, "M24": 0, "M0": 0, "M6": 5, "M16": 6, "M5": 6, "M11": 6, "M14": 6, "M18": 6, "M21": 6, "M3": 6, "M13": 6, "M25": 6, "M22": 6}}, "possible_solutions": []}