{"meta": {"p1": 0.02, "p2": 0.4}, "size": 30, "males_pref": {"M0": {"W22": 0, "W16": 0}, "M1": {"W5": 0, "W13": 1}, "M2": {"W19": 0, "W13": 0, "W24": 0}, "M3": {"W0": 0, "W3": 1, "W17": 2, "W5": 2, "W2": 2}, "M4": {"W4": 0, "W26": 1, "W22": 1, "W10": 1}, "M5": {"W9": 0, "W4": 1}, "M6": {"W12": 0, "W19": 1}, "M7": {"W10": 0, "W6": 0, "W7": 0}, "M8": {"W0": 0, "W14": 0, "W11": 0}, "M9": {"W21": 0, "W2": 0}, "M10": {"W12": 0, "W8": 0, "W1": 2}, "M11": {"W24": 0, "W21": 1}, "M12": {"W10": 0, "W22": 0}, "M13": {"W16": 0, "W17": 0}, "M14": {"W18": 0, "W8": 0}, "M15": {"W13": 0, "W14": 1, "W1": 2}, "M16": {"W4": 0, "W1": 0, "W29": 2}, "M17": {"W8": 0, "W19": 0, "W4": 2, "W29": 2}, "M18": {"W6": 0, "W8": 1}, "M19": {"W15": 0, "W26": 0}, "M20": {"W29": 0, "W10": 0}, "M21": {"W16": 0, "W6": 0, "W27": 0}, "M22": {"W26": 0, "W2": 0}, "M23": {"W11": 0, "W6": 0}, "M24": {"W11": 0, "W16": 0, "W28": 2}, "M25": {"W1": 0, "W16": 0}, "M26": {"W2": 0, "W27": 1}, "M27": {"W24": 0, "W29": 0}, "M28": {"W20": 0, "W21": 0, "W18": 0, "W10": 3, "W13": 4}, "M29": {"W11": 0, "W9": 0, "W12": 0}}, "females_pref": {"W0": {"M26": 0, "M5": 0, "M7": 0, "M25": 0}, "W1": {"M5": 0, "M12": 1, "M15": 2, "M29": 2}, "W2": {"M5": 0, "M25": 1, "M23": 1, "M27": 3}, "W3": {"M14": 0, "M1": 0, "M27": 0}, "W4": {"M24": 0, "M21": 1, "M17": 1, "M2": 3}, "W5": {"M18": 0, "M26": 0, "M17": 0}, "W6": {"M4": 0, "M5": 0}, "W7": {"M6": 0, "M11": 0}, "W8": {"M25": 0, "M14": 0, "M19": 0}, "W9": {"M20": 0, "M13": 0}, "W10": {"M1": 0, "M13": 1}, "W11": {"M21": 0, "M1": 1, "M19": 1}, "W12": {"M2": 0, "M16": 0}, "W13": {"M8": 0, "M18": 1}, "W14": {"M16": 0, "M10": 1}, "W15": {"M16": 0, "M15": 0}, "W16": {"M10": 0, "M26": 0}, "W17": {"M9": 0, "M12": 0, "M13": 0}, "W18": {"M28": 0, "M24": 1}, "W19": {"M29": 0, "M15": 0}, "W20": {"M0": 0, "M5": 0, "M13": 2}, "W21": {"M4": 0, "M25": 0}, "W22": {"M27": 0, "M9": 0}, "W23": {"M9": 0, "M28": 0}, "W24": {"M21": 0, "M8": 1, "M14": 1}, "W25": {"M15": 0, "M4": 1, "M21": 2, "M12": 3, "M11": 4}, "W26": {"M20": 0, "M0": 0, "M11": 2, "M18": 2}, "W27": {"M16": 0, "M19": 0}, "W28": {"M18": 0, "M15": 0}, "W29": {"M28": 0, "M29": 0}}, "possible_solutions": []}