{"meta": {"p1": 0.04, "p2": 0.14}, "size": 16, "males_pref": {"M0": {"W0": 0, "W10": 0, "W2": 0}, "M1": {"W2": 0, "W10": 1, "W13": 1}, "M2": {"W7": 0, "W10": 0}, "M3": {"W6": 0, "W12": 0, "W13": 0}, "M4": {"W7": 0, "W12": 0}, "M5": {"W14": 0, "W12": 0}, "M6": {"W11": 0, "W13": 0}, "M7": {"W14": 0, "W5": 0, "W10": 0, "W4": 0, "W7": 0}, "M8": {"W0": 0, "W8": 0}, "M9": {"W0": 0, "W15": 1}, "M10": {"W11": 0, "W3": 0}, "M11": {"W2": 0, "W15": 0}, "M12": {"W12": 0, "W14": 0}, "M13": {"W2": 0, "W0": 0}, "M14": {"W11": 0, "W15": 0}, "M15": {"W0": 0, "W5": 0}}, "females_pref": {"W0": {"M4": 0, "M8": 1, "M13": 1, "M5": 1}, "W1": {"M10": 0, "M1": 0}, "W2": {"M5": 0, "M12": 0, "M8": 2}, "W3": {"M15": 0, "M10": 0}, "W4": {"M0": 0, "M10": 0, "M12": 0}, "W5": {"M15": 0, "M5": 0}, "W6": {"M8": 0, "M2": 0, "M11": 0}, "W7": {"M5": 0, "M6": 1, "M3": 1}, "W8": {"M9": 0, "M14": 0}, "W9": {"M11": 0, "M9": 0, "M4": 0, "M2": 0}, "W10": {"M8": 0, "M1": 0}, "W11": {"M15": 0, "M8": 1, "M11": 1, "M9": 1}, "W12": {"M5": 0, "M7": 1, "M3": 1}, "W13": {"M7": 0, "M4": 0}, "W14": {"M11": 0, "M3": 0, "M5": 0, "M9": 0}, "W15": {"M8": 0, "M0": 1, "M1": 1}}, "possible_solutions": []}